mimocorb/__init__.py
mimocorb/_version_info.py
mimocorb/activity_logger.py
mimocorb/buffer_control.py
mimocorb/bufferinfoGUI.py
mimocorb/histogram_buffer.py
mimocorb/mimo_buffer.py
mimocorb/parquetReader.py
mimocorb/plot_buffer.py
mimocorb/pulseSimulator.py
mimocorb-1.0.2.dist-info/LICENSE
mimocorb-1.0.2.dist-info/METADATA
mimocorb-1.0.2.dist-info/WHEEL
mimocorb-1.0.2.dist-info/top_level.txt
mimocorb-1.0.2.dist-info/RECORD
