Metadata-Version: 2.1
Name: mimocorb
Version: 1.0.2
Summary: multi-in multi-out Configurable Ring Buffer for Data Acquisition and Visualisation
Author: Christoph Mayer
Author-email: Günter Quast <Guenter.Quast@online.de>, Klaus Heitlinger <HeitILNK@t-online.de>
License: MIT BSD 2-Clause License
Project-URL: Homepage, http://www.etp.kit.edu/~quast/
Keywords: karlsruhe,data,lab,laboratory,practical course,education,acquisition,university,students,physics
Classifier: License :: OSI Approved :: MIT License
Classifier: Development Status :: 5 - Production/Stable
Classifier: Intended Audience :: Education
Classifier: Intended Audience :: Science/Research
Classifier: Topic :: Education
Classifier: Topic :: Scientific/Engineering
Classifier: Topic :: Scientific/Engineering :: Physics
Classifier: Topic :: Scientific/Engineering :: Visualization
Classifier: Programming Language :: Python :: 3
Classifier: Programming Language :: Python :: 3.9
Classifier: Programming Language :: Python :: 3.10
Classifier: Programming Language :: Python :: 3.11
Classifier: Programming Language :: Python :: 3.12
Requires-Python: >=3.9
License-File: LICENSE
Requires-Dist: NumPy
Requires-Dist: Scipy
Requires-Dist: Pandas
Requires-Dist: pyarrow
Requires-Dist: matplotlib
Requires-Dist: pyyaml
Requires-Dist: tk
